yamongo/__init__.py
yamongo-0.0.3.dist-info/LICENSE
yamongo-0.0.3.dist-info/METADATA
yamongo-0.0.3.dist-info/WHEEL
yamongo-0.0.3.dist-info/top_level.txt
yamongo-0.0.3.dist-info/RECORD
