Metadata-Version: 2.1
Name: yamongo
Version: 0.0.3
Summary: Easy to use access to MongoDb databases for basic operations
Author-email: Joakim Wassberg <joakim@arthead.se>
Project-URL: Homepage, https://github.com/arthead-development/yamongo
Keywords: MongoDB,Database,pymongo
Requires-Python: >=3.6.2
License-File: LICENSE
Requires-Dist: pymongo (>=4.1.1)
